ts3ekkoutil/__init__.py
ts3ekkoutil/envconsts.py
ts3ekkoutil/helpers.py
ts3ekkoutil/parser.py
ts3ekkoutil-0.0.20.dist-info/METADATA
ts3ekkoutil-0.0.20.dist-info/WHEEL
ts3ekkoutil-0.0.20.dist-info/top_level.txt
ts3ekkoutil-0.0.20.dist-info/RECORD
