Metadata-Version: 2.1
Name: ts3ekkoutil
Version: 0.0.20
Summary: A collection of utility methods used in the ts3ekkoclient, ts3ekkomanage and ts3ekkosingle modules.
Home-page: https://gitlab.com/networkjanitor/ts3ekkoutil
Author: Xyoz Netsphere
Author-email: nanoowl@xyooz.net
License: MIT
Platform: UNKNOWN
Classifier: Development Status :: 3 - Alpha
Classifier: License :: OSI Approved :: MIT License
Classifier: Programming Language :: Python :: 3
Classifier: Programming Language :: Python :: 3.6
Classifier: Programming Language :: Python :: 3.7
